PySide6_GlobalHotkeys/__init__.py
PySide6_GlobalHotkeys/appid.py
PySide6_GlobalHotkeys/dbuspaths.py
PySide6_GlobalHotkeys/notifications.py
PySide6_GlobalHotkeys/registration.py
pyside6_globalhotkeys-0.0.3.dist-info/licenses/LICENSE
pyside6_globalhotkeys-0.0.3.dist-info/METADATA
pyside6_globalhotkeys-0.0.3.dist-info/WHEEL
pyside6_globalhotkeys-0.0.3.dist-info/top_level.txt
pyside6_globalhotkeys-0.0.3.dist-info/RECORD
